<?xml version="1.0" encoding="UTF-8"?>
<launch4jConfig>
  <dontWrapJar>false</dontWrapJar>
  <headerType>gui</headerType>
  <jar>D:\4 Games\My Games\Ace Alley Office System\Ace Alley Office System.jar</jar>
  <outfile>D:\4 Games\My Games\Ace Alley Office System\Ace Alley Office System.exe</outfile>
  <errTitle>Java is not installed, Click to Intall...</errTitle>
  <cmdLine></cmdLine>
  <chdir>.</chdir>
  <priority>normal</priority>
  <downloadUrl>https://adoptium.net/en-GB/temurin/releases/?version=8</downloadUrl>
  <supportUrl></supportUrl>
  <stayAlive>false</stayAlive>
  <restartOnCrash>false</restartOnCrash>
  <manifest></manifest>
  <icon>D:\4 Games\My Games\Ace Alley Office System\AceAlleyLogo.ico</icon>
  <jre>
    <path>%JAVA_HOME%;%PATH%</path>
    <requiresJdk>false</requiresJdk>
    <requires64Bit>false</requires64Bit>
    <minVersion></minVersion>
    <maxVersion></maxVersion>
  </jre>
</launch4jConfig>